MANIFEST.in
README.md
setup.py
azurerm/__init__.py
azurerm/acs.py
azurerm/adalfns.py
azurerm/amsrp.py
azurerm/computerp.py
azurerm/container.py
azurerm/cosmosdbrp.py
azurerm/deployments.py
azurerm/graphfns.py
azurerm/insightsrp.py
azurerm/keyvault.py
azurerm/networkrp.py
azurerm/resourcegroups.py
azurerm/restfns.py
azurerm/settings.py
azurerm/storagerp.py
azurerm/subfns.py
azurerm/templates.py
azurerm/vmimages.py
azurerm.egg-info/PKG-INFO
azurerm.egg-info/SOURCES.txt
azurerm.egg-info/dependency_links.txt
azurerm.egg-info/not-zip-safe
azurerm.egg-info/requires.txt
azurerm.egg-info/top_level.txt