Metadata-Version: 1.0
Name: azurerm
Version: 0.9.14
Summary: Azure Resource Manager REST wrappers
Home-page: http://github.com/gbowerman/azurerm
Author: sendmarsh
Author-email: guybo@outlook.com
License: MIT
Platform: UNKNOWN
